pdfexport/__init__.py
pdfexport/__main__.py
pdfexport/file_to_pdf.py
pdfexport/server.py
pdfexport/config/__init__.py
pdfexport-0.1.3.dist-info/METADATA
pdfexport-0.1.3.dist-info/WHEEL
pdfexport-0.1.3.dist-info/entry_points.txt
pdfexport-0.1.3.dist-info/RECORD
